{
  "0,0": {
    "SourceVersionHash": "LUq1Gq4eFmnMnuQcXRkWuIMZGI8=",
    "VersionHash": "QyHSQruW3fGke8KLbw66eLlHY6U="
  },
  "1,0": {
    "SourceVersionHash": "HuZ/4c27om401YIgLh3Du0a5y3o=",
    "VersionHash": "QyHSQruW3fGke8KLbw66eLlHY6U="
  },
  "0,1": {
    "SourceVersionHash": "ar/tiQwHlHmaVu1FYVA10PF4wLA=",
    "VersionHash": "QyHSQruW3fGke8KLbw66eLlHY6U="
  },
  "1,1": {
    "SourceVersionHash": "HuxTIQuRhJN92maHT4p72G0C6VQ=",
    "VersionHash": "tKG8STWzEw6uKNdY8jNT4ipz4Uo="
  },
  "2,0": {
    "SourceVersionHash": "rGUZb1oAXPD/4gFoVOuKDJd1wfc=",
    "VersionHash": "QyHSQruW3fGke8KLbw66eLlHY6U="
  },
  "2,1": {
    "SourceVersionHash": "FUkxBVfFuOrLQU8G0nv+hTa8NW4=",
    "VersionHash": "QyHSQruW3fGke8KLbw66eLlHY6U="
  },
  "0,2": {
    "SourceVersionHash": "KTSaNnsARsuW7yoNpkYLGqnS2jg=",
    "VersionHash": "QyHSQruW3fGke8KLbw66eLlHY6U="
  },
  "1,2": {
    "SourceVersionHash": "KTSaNnsARsuW7yoNpkYLGqnS2jg=",
    "VersionHash": "QyHSQruW3fGke8KLbw66eLlHY6U="
  },
  "2,2": {
    "SourceVersionHash": "KTSaNnsARsuW7yoNpkYLGqnS2jg=",
    "VersionHash": "QyHSQruW3fGke8KLbw66eLlHY6U="
  }
}